canalyst_candas/__init__.py
canalyst_candas/candas_datareader.py
canalyst_candas/datafunctions.py
canalyst_candas/exceptions.py
canalyst_candas/settings.py
canalyst_candas/version.py
canalyst_candas/candas/__init__.py
canalyst_candas/candas/chart.py
canalyst_candas/candas/func_music.py
canalyst_candas/candas/model.py
canalyst_candas/candas/modelset.py
canalyst_candas/candas/sample_model.py
canalyst_candas/candas/search.py
canalyst_candas/configuration/__init__.py
canalyst_candas/configuration/config.py
canalyst_candas/configuration/exceptions.py
canalyst_candas/fonts/Barlow-OFL-License.txt
canalyst_candas/fonts/Barlow-SemiBold.ttf
canalyst_candas/fonts/Roboto-License.txt
canalyst_candas/fonts/Roboto-Regular.ttf
canalyst_candas/images/logo.png
canalyst_candas/sample_data/drivers/DIS US_drivers.json
canalyst_candas/sample_data/drivers/NFLX US_drivers.json
canalyst_candas/sample_data/drivers/TSLA US_drivers.json
canalyst_candas/sample_data/models/DIS US_forecast_data.csv
canalyst_candas/sample_data/models/DIS US_historical_data.csv
canalyst_candas/sample_data/models/DIS US_name_index.csv
canalyst_candas/sample_data/models/NFLX US_forecast_data.csv
canalyst_candas/sample_data/models/NFLX US_historical_data.csv
canalyst_candas/sample_data/models/NFLX US_name_index.csv
canalyst_candas/sample_data/models/Netflix NFLX US.xlsx
canalyst_candas/sample_data/models/TSLA US_forecast_data.csv
canalyst_candas/sample_data/models/TSLA US_historical_data.csv
canalyst_candas/sample_data/models/TSLA US_name_index.csv
canalyst_candas/sample_data/models/Tesla TSLA US.xlsx
canalyst_candas/sample_data/models/The Walt Disney Company DIS US.xlsx
canalyst_candas/tests/__init__.py
canalyst_candas/tests/test_utils.py
canalyst_candas/tests/test_utils_get_data_set_from_mds.py
canalyst_candas/tests/test_utils_get_historical_periods.py
canalyst_candas/tests/test_utils_get_info_from_ticker.py
canalyst_candas/tests/test_utils_get_sample_drivers.py
canalyst_candas/tests/test_utils_get_test_data_set.py
canalyst_candas-0.0.47.dist-info/LICENSE
canalyst_candas-0.0.47.dist-info/METADATA
canalyst_candas-0.0.47.dist-info/WHEEL
canalyst_candas-0.0.47.dist-info/top_level.txt
canalyst_candas-0.0.47.dist-info/RECORD
