Metadata-Version: 2.1
Name: canalyst_candas
Version: 0.0.47
Summary: The official Canalyst Software Development Kit (SDK) for our public API
Author: Canalyst
Author-email: support+api@canalyst.com
License: Apache-2.0
Classifier: Programming Language :: Python :: 3
Classifier: License :: OSI Approved :: Apache Software License
Classifier: Operating System :: OS Independent
Requires-Python: >=3.7
License-File: LICENSE
Requires-Dist: boto>=2.49.0
Requires-Dist: boto3>=1.17.27
Requires-Dist: botocore>=1.20.27
Requires-Dist: fred>=3.1
Requires-Dist: fredapi>=0.4.3
Requires-Dist: future>=0.18.2
Requires-Dist: graphviz>=0.16
Requires-Dist: joblib>=1.0.1
Requires-Dist: networkx>=2.5.1
Requires-Dist: numexpr>=2.7.1
Requires-Dist: numpy>=1.19.2
Requires-Dist: pandas>=1.2.3
Requires-Dist: plotly>=4.14.3
Requires-Dist: pydantic>=1.8.2
Requires-Dist: pydot>=1.4.2
Requires-Dist: python-graphql-client>=0.4.3
Requires-Dist: pyvis>=0.1.9
Requires-Dist: openpyxl>=3.0.7
Requires-Dist: requests>=2.24.0
Requires-Dist: requests-html>=0.10.0
Requires-Dist: urllib3>=1.25.11
Requires-Dist: matplotlib>=3.4.3
Requires-Dist: statsmodels>=0.12.2
Requires-Dist: yahoo-fin>=0.8.9.1
Requires-Dist: pyarrow==17.0.0
